tallyfy/__init__.py
tallyfy/core.py
tallyfy/models.py
tallyfy/__pycache__/__init__.cpython-310.pyc
tallyfy/__pycache__/core.cpython-310.pyc
tallyfy/__pycache__/form_fields_management.cpython-310.pyc
tallyfy/__pycache__/models.cpython-310.pyc
tallyfy/__pycache__/task_management.cpython-310.pyc
tallyfy/__pycache__/template_management.cpython-310.pyc
tallyfy/__pycache__/user_management.cpython-310.pyc
tallyfy/form_fields_management/__init__.py
tallyfy/form_fields_management/base.py
tallyfy/form_fields_management/crud_operations.py
tallyfy/form_fields_management/options_management.py
tallyfy/form_fields_management/suggestions.py
tallyfy/form_fields_management/__pycache__/__init__.cpython-310.pyc
tallyfy/form_fields_management/__pycache__/base.cpython-310.pyc
tallyfy/form_fields_management/__pycache__/crud_operations.cpython-310.pyc
tallyfy/form_fields_management/__pycache__/options_management.cpython-310.pyc
tallyfy/form_fields_management/__pycache__/suggestions.cpython-310.pyc
tallyfy/organization_management/__init__.py
tallyfy/organization_management/base.py
tallyfy/organization_management/retrieval.py
tallyfy/task_management/__init__.py
tallyfy/task_management/base.py
tallyfy/task_management/creation.py
tallyfy/task_management/retrieval.py
tallyfy/task_management/search.py
tallyfy/task_management/__pycache__/__init__.cpython-310.pyc
tallyfy/task_management/__pycache__/base.cpython-310.pyc
tallyfy/task_management/__pycache__/creation.cpython-310.pyc
tallyfy/task_management/__pycache__/retrieval.cpython-310.pyc
tallyfy/task_management/__pycache__/search.cpython-310.pyc
tallyfy/template_management/__init__.py
tallyfy/template_management/analysis.py
tallyfy/template_management/automation.py
tallyfy/template_management/base.py
tallyfy/template_management/basic_operations.py
tallyfy/template_management/health_assessment.py
tallyfy/user_management/__init__.py
tallyfy/user_management/base.py
tallyfy/user_management/invitation.py
tallyfy/user_management/retrieval.py
tallyfy-1.0.17.dist-info/licenses/LICENSE
tallyfy-1.0.17.dist-info/METADATA
tallyfy-1.0.17.dist-info/WHEEL
tallyfy-1.0.17.dist-info/top_level.txt
tallyfy-1.0.17.dist-info/RECORD
