Metadata-Version: 2.4
Name: tallyfy
Version: 1.0.17
Summary: A comprehensive Python SDK for interacting with the Tallyfy API
Home-page: https://github.com/tallyfy/sdk
Author: Tallyfy
Author-email: Tallyfy <support@tallyfy.com>
Maintainer-email: Tallyfy <support@tallyfy.com>
License: MIT
Project-URL: Documentation, https://tallyfy.com/products/
Project-URL: Repository, https://github.com/tallyfy/sdk
Project-URL: Bug Tracker, https://github.com/tallyfy/sdk/issues
Project-URL: Changelog, https://github.com/tallyfy/sdk/blob/main/CHANGELOG.md
Keywords: tallyfy,api,sdk,workflow,automation,task,management
Classifier: Development Status :: 5 - Production/Stable
Classifier: Intended Audience :: Developers
Classifier: License :: OSI Approved :: MIT License
Classifier: Operating System :: OS Independent
Classifier: Programming Language :: Python :: 3
Classifier: Programming Language :: Python :: 3.7
Classifier: Programming Language :: Python :: 3.8
Classifier: Programming Language :: Python :: 3.9
Classifier: Programming Language :: Python :: 3.10
Classifier: Programming Language :: Python :: 3.11
Classifier: Programming Language :: Python :: 3.12
Classifier: Topic :: Software Development :: Libraries :: Python Modules
Classifier: Topic :: Office/Business :: Scheduling
Classifier: Topic :: Internet :: WWW/HTTP :: Dynamic Content
Requires-Python: >=3.7
License-File: LICENSE
Requires-Dist: requests>=2.25.0
Requires-Dist: typing-extensions>=4.0.0; python_version < "3.8"
Requires-Dist: email-validator==2.2.0
Provides-Extra: dev
Requires-Dist: pytest>=6.0.0; extra == "dev"
Requires-Dist: pytest-cov>=2.10.0; extra == "dev"
Requires-Dist: black>=21.0.1; extra == "dev"
Requires-Dist: flake8>=3.8.0; extra == "dev"
Requires-Dist: mypy>=0.800; extra == "dev"
Dynamic: author
Dynamic: home-page
Dynamic: license-file
Dynamic: requires-python
